<?xml version="1.0" encoding="utf-8"?>
<Resources Culture="ru-RU">
	<Group Type="String">
		<Items>
			<Item Name="Caption" Value="Схема раздела: &quot;Идентификатор компании&quot;" />
			<Item Name="LocalizableStrings.Caption.Value" Value="Идентификатор компании" />
			<Item Name="LocalizableStrings.GKITlrRequestButtonCaption.Value" Value="Запросить лицензии" />
			<Item Name="LocalizableStrings.GKITlsDownloadButtonCaption.Value" Value="Загрузить лицензии" />
			<Item Name="LocalizableStrings.GKITlsInstallButtonCaption.Value" Value="Установить лицензии" />
		</Items>
	</Group>
</Resources>