{
  "PackageData": [
    {
      "Row": [
        {
          "SchemaColumnUId": "ae0e45ca-c495-4fe7-a39d-3ab7278e1617",
          "Value": "05ab5f2d-04d6-428a-8219-9fde0c8536b1"
        },
        {
          "SchemaColumnUId": "a215f575-7283-41bd-8852-b2415a935051",
          "Value": ""
        },
        {
          "SchemaColumnUId": "78ed4015-b81f-49fc-9d50-847cf8df5e6c",
          "Value": 0
        },
        {
          "SchemaColumnUId": "fb750eb9-35b6-463e-b3b8-1a69ec871e43",
          "Value": ""
        },
        {
          "SchemaColumnUId": "551ce105-25dc-4a76-b318-cf37635e88c3",
          "Value": "{\"Gauged692e6f0-b5fc-4380-be27-0f7ea19f0c31\":{\"widgetType\":\"Gauge\",\"parameters\":{\"caption\":\"Активные лицензии\",\"sectionBindingColumn\":\"GKILicPackage\",\"sectionId\":\"910de435-efa7-496d-a881-3c59b7cc95a7\",\"entitySchemaName\":\"GKILic\",\"filterData\":\"{\\\"className\\\":\\\"Terrasoft.FilterGroup\\\",\\\"items\\\":{},\\\"logicalOperation\\\":0,\\\"isEnabled\\\":true,\\\"filterType\\\":6,\\\"rootSchemaName\\\":\\\"GKILic\\\",\\\"key\\\":\\\"\\\"}\",\"aggregationType\":2,\"aggregationColumn\":\"GKIAvailableCount\",\"format\":{\"thousandSeparator\":\" \",\"type\":4,\"dateFormat\":\"d.m.Y\"},\"style\":\"widget-green\",\"orderDirection\":2,\"min\":0,\"middleFrom\":7,\"middleTo\":15,\"max\":20}},\"Indicator8b082c1a-378e-4fe8-80d7-06e180a5adac\":{\"widgetType\":\"Indicator\",\"parameters\":{\"caption\":\"Количество приложений\",\"sectionBindingColumn\":\"GKILicPackage\",\"sectionId\":\"910de435-efa7-496d-a881-3c59b7cc95a7\",\"entitySchemaName\":\"GKIInstanceLicPackage\",\"filterData\":\"{\\\"className\\\":\\\"Terrasoft.FilterGroup\\\",\\\"items\\\":{},\\\"logicalOperation\\\":0,\\\"isEnabled\\\":true,\\\"filterType\\\":6,\\\"rootSchemaName\\\":\\\"GKIInstanceLicPackage\\\",\\\"key\\\":\\\"\\\"}\",\"aggregationType\":1,\"columnName\":null,\"format\":{\"textDecorator\":\"{0}\",\"type\":4,\"decimalPrecision\":0},\"style\":\"widget-dark-turquoise\",\"fontStyle\":\"big-indicator-font-size\"}},\"Chart80563b13-6a9e-4e7b-8ad6-97669ec7f8a8\":{\"widgetType\":\"Chart\",\"parameters\":{\"seriesConfig\":[],\"orderBy\":\"GroupByField\",\"orderDirection\":\"Ascending\",\"caption\":\"Распределено\",\"sectionId\":\"910de435-efa7-496d-a881-3c59b7cc95a7\",\"xAxisDefaultCaption\":null,\"yAxisDefaultCaption\":null,\"useEmptyValue\":false,\"isStackedChart\":false,\"primaryColumnName\":\"Id\",\"yAxisConfig\":{\"position\":0},\"schemaName\":\"GKILicUserInstanceLicPackage\",\"sectionBindingColumn\":\"GKILicPackage\",\"func\":1,\"type\":\"pie\",\"xAxisColumn\":\"GKISyncedState\",\"styleColor\":\"widget-violet\",\"filterData\":\"{\\\"className\\\":\\\"Terrasoft.FilterGroup\\\",\\\"items\\\":{},\\\"logicalOperation\\\":0,\\\"isEnabled\\\":true,\\\"filterType\\\":6,\\\"rootSchemaName\\\":\\\"GKILicUserInstanceLicPackage\\\",\\\"key\\\":\\\"\\\"}\",\"format\":{\"type\":4,\"decimalPrecision\":0},\"isLegendEnabled\":false}}}"
        },
        {
          "SchemaColumnUId": "9eedf8ab-d02e-4a4a-9f9d-19ede1c873bc",
          "Value": "null",
          "DisplayValue": ""
        }
      ]
    }
  ]
}